nipype2pydra/__init__.py
nipype2pydra/_version.py
nipype2pydra/exceptions.py
nipype2pydra/helpers.py
nipype2pydra/package.py
nipype2pydra/symbols.py
nipype2pydra/testing.py
nipype2pydra/workflow.py
nipype2pydra/cli/__init__.py
nipype2pydra/cli/base.py
nipype2pydra/cli/convert.py
nipype2pydra/cli/pkg_gen.py
nipype2pydra/interface/__init__.py
nipype2pydra/interface/base.py
nipype2pydra/interface/loaders.py
nipype2pydra/interface/python.py
nipype2pydra/interface/shell.py
nipype2pydra/interface/nipype-ports/compute_dvars.yaml
nipype2pydra/interface/nipype-ports/compute_dvars_callables.py
nipype2pydra/interface/nipype-ports/framewise_displacement.yaml
nipype2pydra/interface/nipype-ports/framewise_displacement_callables.py
nipype2pydra/interface/nipype-ports/non_steady_state_detector.yaml
nipype2pydra/interface/nipype-ports/non_steady_state_detector_callables.py
nipype2pydra/interface/nipype-ports/tsnr.yaml
nipype2pydra/interface/nipype-ports/tsnr_callables.py
nipype2pydra/interface/tests/test_interface.py
nipype2pydra/pkg_gen/__init__.py
nipype2pydra/pkg_gen/resources/templates/NOTICE
nipype2pydra/pkg_gen/resources/templates/README.rst
nipype2pydra/pkg_gen/resources/templates/init.py
nipype2pydra/pkg_gen/resources/templates/nipype-auto-convert-requirements.txt
nipype2pydra/pkg_gen/resources/templates/gh_workflows/ci-cd-interface.yaml
nipype2pydra/pkg_gen/resources/templates/gh_workflows/ci-cd-workflow.yaml
nipype2pydra/pkg_gen/resources/templates/related-packages/conftest_.py
nipype2pydra/pkg_gen/resources/templates/related-packages/fileformats/LICENSE
nipype2pydra/pkg_gen/resources/templates/related-packages/fileformats/README.rst
nipype2pydra/pkg_gen/resources/templates/related-packages/fileformats/pyproject.toml
nipype2pydra/pkg_gen/resources/templates/related-packages/fileformats/fileformats/medimage_CHANGEME/__init__.py
nipype2pydra/pkg_gen/resources/templates/related-packages/fileformats-extras/LICENSE
nipype2pydra-0.5.0.dist-info/METADATA
nipype2pydra-0.5.0.dist-info/WHEEL
nipype2pydra-0.5.0.dist-info/entry_points.txt
nipype2pydra-0.5.0.dist-info/licenses/LICENSE
nipype2pydra-0.5.0.dist-info/RECORD
