Metadata-Version: 2.4
Name: nipype2pydra
Version: 0.5.0
Summary: Tool for converting Nipype tasks and workflows into Pydra syntax
Project-URL: repository, https://github.com/nipype/nipype2pydra
Author-email: "Thomas G. Close" <tom.g.close@gmail.com>
Maintainer-email: "Thomas G. Close" <tom.g.close@gmail.com>
License: Creative Commons Attribution 4.0 International Public License
License-File: LICENSE
Keywords: converters,data,nipype,pydra,workflows
Classifier: Development Status :: 3 - Alpha
Classifier: Environment :: Console
Classifier: Intended Audience :: Science/Research
Classifier: License :: OSI Approved :: Apache Software License
Classifier: Operating System :: MacOS :: MacOS X
Classifier: Operating System :: Microsoft :: Windows
Classifier: Operating System :: POSIX :: Linux
Classifier: Programming Language :: Python :: 3.8
Classifier: Programming Language :: Python :: 3.9
Classifier: Programming Language :: Python :: 3.10
Classifier: Programming Language :: Python :: 3.11
Classifier: Topic :: Scientific/Engineering
Requires-Python: >=3.7
Requires-Dist: attrs>=22.1.0
Requires-Dist: black
Requires-Dist: fileformats-datascience
Requires-Dist: fileformats-medimage>=0.4
Requires-Dist: fileformats>=0.8
Requires-Dist: nipype
Requires-Dist: pydra>=1.0a
Requires-Dist: pyyaml>=6.0
Requires-Dist: requests>=2.31.0
Requires-Dist: toml
Requires-Dist: tqdm
Requires-Dist: traits
Requires-Dist: typing-extensions
Provides-Extra: dev
Requires-Dist: codespell; extra == 'dev'
Requires-Dist: flake8; extra == 'dev'
Requires-Dist: flake8-pyproject; extra == 'dev'
Requires-Dist: pre-commit; extra == 'dev'
Provides-Extra: docs
Requires-Dist: docutils>=0.10; extra == 'docs'
Requires-Dist: furo>=2022.2.14.1; extra == 'docs'
Requires-Dist: mock>1.0; extra == 'docs'
Requires-Dist: numpydoc>=0.6.0; extra == 'docs'
Requires-Dist: packaging; extra == 'docs'
Requires-Dist: sphinx-argparse>=0.2.0; extra == 'docs'
Requires-Dist: sphinx-click>=3.1; extra == 'docs'
Requires-Dist: sphinx>=2.1.2; extra == 'docs'
Provides-Extra: test
Requires-Dist: datalad; extra == 'test'
Requires-Dist: fileformats-medimage-afni; extra == 'test'
Requires-Dist: fileformats-medimage-extras; extra == 'test'
Requires-Dist: nipy; extra == 'test'
Requires-Dist: nireports; extra == 'test'
Requires-Dist: nirodents; extra == 'test'
Requires-Dist: nitime; extra == 'test'
Requires-Dist: niworkflows; extra == 'test'
Requires-Dist: pytest-cov>=2.12.1; extra == 'test'
Requires-Dist: pytest-env>=0.6.2; extra == 'test'
Requires-Dist: pytest>=6.2.5; extra == 'test'
